{
"type": "FeatureCollection",
"crs": { "type": "name", "properties": { "name": "urn:ogc:def:crs:EPSG::3857" } },
                                                                                
"features": [
{ "type": "Feature", "properties": { "City": "Mesa", "Initiative": "Green Building", "Location": "3361 S. Signal Butte Road  Fire Station 219", "Latitude": 33.353433, "Longitude": -111.600479, "Building": "Fire Station No. 219", "URL_1": "<a href =\"http:\/\/www.mesaaz.gov\/sustainability\/pdf\/Mesa_Fire_Station_219_LEED.pdf\">Learn more about station 219 solar power<\/a>", "Info": "Gold", "Describe": "The goal was LEED silver, but the outcome was LEED gold. This Mesa fire station is a great role model for other sustainability efforts in the city and is one of the first LEED certified City of Mesa buildings." }, "geometry": { "type": "Point", "coordinates": [ -12423308.49456542, 3942310.7968302178 ] } },
{ "type": "Feature", "properties": { "City": "Mesa", "Initiative": "Green Building", "Location": "Fire Station 220  5763 E Main St. Mesa  AZ 85205", "Latitude": 33.415210, "Longitude": -111.705627, "Building": "Fire Station No. 220", "URL_1": "<a href =\"http:\/\/www.mesaaz.gov\/sustainability\/pdf\/Mesa_Fire_Station_220_LEED.pdf\">Learn more about station 220 solar power<\/a>", "Info": "Gold", "Describe": "One of the first LEED certified city of Mesa buildings. 7.5% of the energy used comes from the sun with a 15.18 kW photovoltaic system." }, "geometry": { "type": "Point", "coordinates": [ -12435013.516383352, 3950546.7219033102 ] } },
{ "type": "Feature", "properties": { "City": "Mesa", "Initiative": "Green Building", "Location": "6555 E Southern Ave, Mesa, AZ", "Latitude": 33.388734, "Longitude": -111.688392, "Building": "Superstition Springs Transit Center", "URL_1": "<a href=\"http:\/\/www.valleymetro.org\/images\/uploads\/sstc_entry_board.pdf\n\">More<\/a>", "Info": "Rainwater harvesting", "Describe": "Green roof captures and guides rain water to plants below" }, "geometry": { "type": "Point", "coordinates": [ -12433261.515628461, 3946792.2581709288 ] } }
]
}
