{
"type": "FeatureCollection",
"crs": { "type": "name", "properties": { "name": "urn:ogc:def:crs:EPSG::3857" } },
                                                                                
"features": [
{ "type": "Feature", "properties": { "wkt_geom": "POINT(-12475861.7582519818097353 3961378.84480516985058784)", "City": "Phoenix", "Initiative": "Land Reuse", "Location": "4141 N 3rd St. Phoenix  AZ  85012", "Latitude": 33.496394, "Longitude": -112.072573, "Building": "Vacant lot", "URL_1": "<a target=\"_blank\" href =\"http:\/\/phxrenews.org\/locations\/indian-school\">Learn more<\/a>", "Info": "15 acres", "Describe": "A vacant lot transformed into 15 acres of public space." }, "geometry": { "type": "Point", "coordinates": [ -12475861.758251982, 3961378.8449211414 ] } }
]
}
